{
  "changePassword": "Change Password",
  "company.createNewCompany": "Create new company",
  "account.createNewUser": "Create new user",
  "reportIssue": "report issue",
  "hi": "Hi",
  "logout": "Logout",
  "noRecordFound": "No record found",
  "click": "Click",
  "here": "Here",
  "goBackToDashboard": "to go back to dashboard",
  "loading": "Loading",
  "loadMore": "Load More",
  "details.noMore": "No more",
  "sign-in.title": "Sign In",
  "timeFrameHours": "hrs",
  "timeFrameDays": "days",
  "cancel": "Cancel",
  "proceed": "Proceed",
  "overview": "Overview",
  "detailsReport": "Details Report",
  "joi.any.unknown": "{key} is not allowed",
  "joi.any.invalid": "{key} contains an invalid value",
  "joi.any.empty": "{key} is not allowed to be empty",
  "joi.any.required": "{key} is required",
  "joi.any.allowOnly": "{key} must be one of {valids}",
  "joi.any.default": "{key} threw an error when running default method",
  "joi.array.base": "{key} must be an array",
  "joi.array.includes": "{key} at position {pos} does not match any of the allowed types",
  "joi.array.includesSingle": "single value of \"{!key}\" does not match any of the allowed types",
  "joi.array.includesOne": "{key} at position {pos} fails because {reason}",
  "joi.array.includesOneSingle": "single value of \"{!key}\" fails because {reason}",
  "joi.array.includesRequiredUnknowns": "{key} does not contain {unknownMisses} required value(s)",
  "joi.array.includesRequiredKnowns": "{key} does not contain {knownMisses}",
  "joi.array.includesRequiredBoth": "{key} does not contain {knownMisses} and {unknownMisses} other required value(s)",
  "joi.array.excludes": "{key} at position {pos} contains an excluded value",
  "joi.array.excludesSingle": "{key} single value of \"{!key}\" contains an excluded value",
  "joi.array.min": "{key} must contain at least {limit} items",
  "joi.array.max": "{key} must contain less than or equal to {limit} items",
  "joi.array.length": "{key} must contain {limit} items",
  "joi.array.ordered": "{key} at position {pos} fails because {reason}",
  "joi.array.orderedLength": "{key} at position {pos} fails because array must contain at most {limit} items",
  "joi.array.sparse": "{key} must not be a sparse array",
  "joi.array.unique": "{key} position {pos} contains a duplicate value",
  "joi.boolean.base": "{key} must be a boolean",
  "joi.binary.base": "{key} must be a buffer or a string",
  "joi.binary.min": "{key} must be at least {limit} bytes",
  "joi.binary.max": "{key} must be less than or equal to {limit} bytes",
  "joi.binary.length": "{key} must be {limit} bytes",
  "joi.date.base": "{key} must be a number of milliseconds or valid date string",
  "joi.date.min": "{key} must be larger than or equal to \"{limit}\"",
  "joi.date.max": "{key} must be less than or equal to \"{limit}\"",
  "joi.date.isoDate": "{key} must be a valid ISO 8601 date",
  "joi.date.timestamp.javascript": "{key} must be a valid timestamp or number of milliseconds",
  "joi.date.timestamp.unix": "{key} must be a valid timestamp or number of seconds",
  "joi.date.ref": "{key} references \"{ref}\" which is not a date",
  "joi.function.base": "{key} must be a Function",
  "joi.function.arity": "{key} must have an arity of {n}",
  "joi.function.minArity": "{key} must have an arity greater or equal to {n}",
  "joi.function.maxArity": "{key} must have an arity lesser or equal to {n}",
  "joi.object.base": "{key} must be an object",
  "joi.object.child": "{key} child \"{!key}\" fails because {reason}",
  "joi.object.min": "{key} must have at least {limit} children",
  "joi.object.max": "{key} must have less than or equal to {limit} children",
  "joi.object.length": "{key} must have {limit} children",
  "joi.object.allowunknown": "{key} is not allowed",
  "joi.object.with": "{key} missing required peer \"{peer}\"",
  "joi.object.without": "{key} conflict with forbidden peer \"{peer}\"",
  "joi.object.missing": "{key} must contain at least one of {peers}",
  "joi.object.xor": "{key} contains a conflict between exclusive peers {peers}",
  "joi.object.or": "{key} must contain at least one of {peers}",
  "joi.object.and": "{key} contains {present} without its required peers {missing}",
  "joi.object.nand": "{key} !!\"{main}\" must not exist simultaneously with {peers}",
  "joi.object.assert": "{key} !!\"{ref}\" validation failed because \"{ref}\" failed to {message}",
  "joi.object.type": "{key} must be an instance of \"{type}\"",
  "joi.object.rename.multiple": "{key} cannot rename child \"{from}\" because multiple renames are disabled and another key was already renamed to \"{to}\"",
  "joi.object.rename.override": "{key} cannot rename child \"{from}\" because override is disabled and target \"{to}\" exists",
  "joi.number.base": "{key} must be a number",
  "joi.number.min": "{key} must be larger than or equal to {limit}",
  "joi.number.max": "{key} must be less than or equal to {limit}",
  "joi.number.less": "{key} must be less than {limit}",
  "joi.number.greater": "{key} must be greater than {limit}",
  "joi.number.float": "{key} must be a float or double",
  "joi.number.integer": "{key} must be an integer",
  "joi.number.negative": "{key} must be a negative number",
  "joi.number.positive": "{key} must be a positive number",
  "joi.number.precision": "{key} must have no more than {limit} decimal places",
  "joi.number.ref": "{key} references \"{ref}\" which is not a number",
  "joi.number.multiple": "{key} must be a multiple of {multiple}",
  "joi.string.base": "{key} must be a string",
  "joi.string.min": "{key} length must be at least {limit} characters long",
  "joi.string.max": "{key} length must be less than or equal to {limit} characters long",
  "joi.string.length": "{key} length must be {limit} characters long",
  "joi.string.alphanum": "{key} must only contain alpha-numeric characters",
  "joi.string.token": "{key} must only contain alpha-numeric and underscore characters",
  "joi.string.regex.base": "{key} fails to match the required pattern {pattern}",
  "joi.string.regex.name": "{key} fails to match the {name} pattern",
  "joi.string.email": "{key} must be a valid email",
  "joi.string.uri": "{key} must be a valid uri",
  "joi.string.uriCustomScheme": "{key} must be a valid uri with a scheme matching the {scheme} pattern",
  "joi.string.isoDate": "{key} must be a valid ISO 8601 date",
  "joi.string.guid": "{key} must be a valid GUID",
  "joi.string.hex": "{key} must only contain hexadecimal characters",
  "joi.string.hostname": "{key} must be a valid hostname",
  "joi.string.lowercase": "{key} must only contain lowercase characters",
  "joi.string.uppercase": "{key} must only contain uppercase characters",
  "joi.string.trim": "{key} must not have leading or trailing whitespace",
  "joi.string.creditCard": "{key} must be a credit card",
  "joi.string.ref": "{key} references \"{ref}\" which is not a number",
  "joi.string.ip": "{key} must be a valid ip address with a {cidr} CIDR",
  "joi.string.ipVersion": "{key} must be a valid ip address of one of the following versions {version} with a {cidr} CIDR",
  "all": "All",
  "onnet": "Onnet",
  "offnet": "Offnet",
  "maaiiIn": "Maaii-In",
  "details.downloadReport": "Download Report",
  "startTime": "Start time",
  "endTime": "End time",
  "type": "Type",
  "calls.overview.monthlyVoiceCallUser": "Monthly Voice Call User (Unique)",
  "calls.overview.callBehaviourStatistics": "Call Behaviour Statistics",
  "calls.overview.totalCallsAttempts": "Total Calls Attempts",
  "calls.overview.totalCallDuration": "Total Call Duration",
  "calls.overview.averageCallDuration": "Average Call Duration",
  "calls.overview.callSuccessAnalytic": "Call Success Analytic",
  "calls.overview.answerSeizureRatio": "Answer Seizure Ratio",
  "calls.overview.callDurationAnalytic": "Call Duration Analytic",
  "calls.details.caller": "Caller",
  "calls.details.callee": "Callee",
  "calls.details.callDuration": "Call Duration",
  "date": "Date",
  "status": "Status",
  "calls.details.lastReponseCode": "Last Response Code",
  "calls.details.byeReason": "Bye Reason",
  "calls.details.releaseParty": "Release Party",
  "period": "Period",
  "endUser.details.walletInfoUnavailable": "Wallet info unavailable",
  "endUser.details.verified": "Verified",
  "endUser.details.unverified": "Unverified",
  "endUser.overview.userDistributionByOs": "User Distribution by OS",
  "endUser.overview.totalUser": "Total User",
  "username": "Username",
  "endUser.details.registrationDate": "Registration Date",
  "endUser.details.accountStatus": "Account Status",
  "endUser.details.latestDeviceModel": "Latest Device Model",
  "buildId": "Build Id",
  "endUser.details.appVersion": "App Version",
  "noMoreResult": "No more result",
  "endUser.details.expirationDate": "Expiration date",
  "endUser.details.lastTopUp": "Last top-up",
  "details.dateAndTime": "Date & Time",
  "im.details.typeAndFilesize": "Type / Filesize",
  "details.mobileAndDestination": "Mobile & Destination",
  "im.details.recipients": "Recipients",
  "overview.welcome": "Welcome",
  "amount": "Amount",
  "remark": "Remark",
  "submitted": "submitted",
  "mobile": "Mobile",
  "wallet": "Wallet",
  "vsdk.overview.total.attempts": "Total number of verification attempts",
  "vsdk.overview.total.success": "Total number of success verification",
  "vsdk.overview.number.failure": "Number of failure verification",
  "vsdk.overview.average.successRate": "Average success rate",
  "vsdk.details.method": "Verification Method",
  "vsdk.details.osType": "OS Type",
  "filter": "Filter",
  "appId": "Application ID",
  "overview.busiestTime": "Busiest Time",
  "attempts": "Attempts",
  "location": "Location",
  "summary": "Summary",
  "vsdk.verificationAttempt": "Verification Attempt",
  "vsdk.overview.top.attempts": "Top 10 numbers of verification attempts in the world",
  "vsdk.name": "Verification",
  "details": "Details",
  "vsdk.details.registeredDate": "Registered Date",
  "success": "Success",
  "failure": "Failure",
  "valid": "Valid",
  "invalid": "Invalid",
  "vsdk.details.ported": "Ported",
  "roaming": "Roaming",
  "matched": "Matched",
  "vsdk.details.notMatched": "Not matched",
  "vsdk.details.resultInfo": "Result Info",
  "vsdk.details.deviceModel": "Device Model",
  "method": "Method",
  "vsdk.details.simCard": "SIM Card",
  "home": "Home",
  "current": "Current",
  "vsdk.details.operator": "Operator",
  "country": "Country",
  "operator": "Operator",
  "vsdk.details.sourceIp": "Source Ip",
  "os": "OS",
  "result": "Result",
  "overview.monthlyStatistic": "Monthly Statistic",
  "vsf.overview.numberOfTotalPurchases": "Number of Total Purchases",
  "dataUpdatedTill": "Data updated till",
  "overview.summary": "Summary",
  "vsf.overview.totalMusicPurchased": "Total Music Purchased",
  "vsf.overview.totalStickersPurchased": "Total Stickers Purchased",
  "vsf.overview.totalSoundEffectPurchased": "Total Sound Effect Purchased",
  "vsf.overview.totalCreditsPurchased": "Total Credits Purchased",
  "platform": "Platform",
  "vsf.virtualItem": "Virtual Item",
  "vsf.transactionId": "Transaction Id"
}